<?xml version="1.0" encoding="iso-8859-1"?><nitf change.date="4 July 2000" change.time="1900" version="-//IPTC-NAA//DTD NITF-XML 2.1//EN"><head><title>Deutsche Telekom kürzt nochmals Investitionen in den Netzausbau</title><meta content="bs" name="category"></meta><meta content="BE,WF" name="ressort"></meta><meta content="BE" name="ressort1"></meta><meta content="WF" name="ressort2"></meta><meta content="3" name="channel"></meta><meta content="AUT,GER,SUI" name="destination"></meta><meta content="pte.de" name="submitter"></meta><docdata><doc-id id-string="020911010"></doc-id><doc.copyright holder="Achim Sawall, email: redaktion@pressetext.de, Tel. +49 - 30 - 632 27 529" year="2002"></doc.copyright><evloc city="Bonn"></evloc><date.issue norm="2002-09-11 09:59:52"></date.issue></docdata></head><body><body.head><hedline><hl1>Deutsche Telekom kürzt nochmals Investitionen in den Netzausbau</hl1><hl2>Firmenbeteiligungen auf dem Prüfstand</hl2></hedline><abstract><p>Die Deutsche Telekom AG &lt;a href=&quot;http://www.dtag.de&quot;&gt;http://www.dtag.de&lt;/a&gt; will die Investitionen weiter zurückfahren. &quot;Bei jeder Tochtergesellschaft wird überlegt, ob Ausgaben für den Netzausbau um ein oder zwei Jahre verschoben oder ganz gestrichen werden können&quot;, berichtet das &quot;Handelsblatt&quot; heute, Mittwoch, unter Berufung auf unternehmensnahe Kreise.  Damit sollen die  Investitionen im laufenden Jahr auf unter acht Mrd. Euro zu gedrückt werden.</p></abstract></body.head><body.content><p>Ein Sprecher der Telekom wollte zu Sparzielen nichts sagen. Er bestätigte aber, dass neben Firmenbeteiligungen der Telekom, den internen Kosten und der Vier-Säulen-Strategie des Konzerns auch die Investitionen auf dem Prüfstand ständen. Wie weiter im Unternehmen zu hören ist, sind Entscheidungen über Beteiligungsverkäufe noch nicht gefallen. Als sehr unwahrscheinlich gilt intern aber inzwischen ein Rückzug aus Osteuropa, über den spekuliert wurde. Die Osteuropa-Beteiligungen seien mehrheitlich hoch profitabel, hieß es. </p></body.content></body></nitf>


