<?xml version="1.0" encoding="iso-8859-1"?><nitf change.date="4 July 2000" change.time="1900" version="-//IPTC-NAA//DTD NITF-XML 2.1//EN"><head><title>Maxtor präsentiert ATA-Festplatte mit 320 GB</title><meta content="ht" name="category"></meta><meta content="BE,JL" name="ressort"></meta><meta content="BE" name="ressort1"></meta><meta content="JL" name="ressort2"></meta><meta content="1" name="channel"></meta><meta content="AUT,GER,SUI" name="destination"></meta><meta content="pte.de" name="submitter"></meta><docdata><doc-id id-string="020910028"></doc-id><doc.copyright holder="Achim Sawall, email: redaktion@pressetext.de, Tel. +49 - 30 - 632 27 529" year="2002"></doc.copyright><evloc city="Milpitas"></evloc><date.issue norm="2002-09-10 12:35:47"></date.issue></docdata></head><body><body.head><hedline><hl1>Maxtor präsentiert ATA-Festplatte mit 320 GB</hl1><hl2>Geeignet für Medien- und Netzwerkspeicherung</hl2></hedline><abstract><p>Maxtor, Hersteller von Festplattenlaufwerken und anderen Datenspeichern, &lt;a href=&quot;http://www.maxtor.com&quot;&gt;http://www.maxtor.com&lt;/a&gt; präsentiert heute, Dienstag, in Milpitas, Kalifornien, neue ATA-Festplatten mit einer Speicherkapazität von bis zu 320 GB. Die MaXLine Produktlinie wurde speziell für unternehmensweite Anwendungen wie Medien- und Netzwerkspeicherung entwickelt.</p></abstract></body.head><body.content><p>Die MaXLine-Produktlinie umfasst die Modelle MaXLine II mit 5400 U/min und einer Speicherkapazität von bis zu 320 GB sowie MaXLine Plus II mit 7200 U/min und bis zu 250 GB. Beide sind mit einer UltraATA/133-Schnittstelle für Datenübertragungsgeschwindigkeiten von bis zu 133 MB pro Sekunde ausgerüstet. In beide Modelle wird zukünftig auch die serielle ATA-Schnittstelle integriert mit einer maximalen Datentransferrate von 150 MB pro Sekunde. Die Lieferung größerer Stückzahlen ist für das vierte Quartal 2002 vorgesehen. Ein Preis steht noch nicht fest. </p></body.content></body></nitf>


